{
  "Influencers": {
    "online": true,
    "error": null,
    "latency": 103,
    "status_code": 200,
    "ssl_days_remaining": 75,
    "content_valid": true,
    "last_check": "2025-05-13 11:20:12",
    "total_checks": 476,
    "successful_checks": 476,
    "uptime": 100.0,
    "alert_sent": false
  },
  "Tesser": {
    "online": true,
    "error": null,
    "latency": 2289,
    "status_code": 200,
    "ssl_days_remaining": 56,
    "content_valid": true,
    "last_check": "2025-05-13 11:20:15",
    "total_checks": 476,
    "successful_checks": 476,
    "uptime": 100.0,
    "alert_sent": false
  }
}