{
  "Influencers": {
    "online": true,
    "error": null,
    "latency": 92,
    "status_code": 200,
    "ssl_days_remaining": 87,
    "content_valid": true,
    "last_check": "2025-07-02 02:01:39",
    "total_checks": 1564,
    "successful_checks": 1564,
    "uptime": 100.0,
    "alert_sent": false
  },
  "Tesser": {
    "online": true,
    "error": null,
    "latency": 3170,
    "status_code": 200,
    "ssl_days_remaining": 66,
    "content_valid": true,
    "last_check": "2025-07-02 02:01:43",
    "total_checks": 1564,
    "successful_checks": 1561,
    "uptime": 99.81,
    "alert_sent": false
  }
}