{
  "Influencers": {
    "online": true,
    "error": null,
    "latency": 159,
    "status_code": 200,
    "ssl_days_remaining": 51,
    "content_valid": true,
    "last_check": "2025-06-06 06:36:05",
    "total_checks": 997,
    "successful_checks": 997,
    "uptime": 100.0,
    "alert_sent": false
  },
  "Tesser": {
    "online": true,
    "error": null,
    "latency": 1899,
    "status_code": 200,
    "ssl_days_remaining": 32,
    "content_valid": true,
    "last_check": "2025-06-06 06:36:07",
    "total_checks": 997,
    "successful_checks": 996,
    "uptime": 99.9,
    "alert_sent": false
  }
}