{
  "Influencers": {
    "online": true,
    "error": null,
    "latency": 137,
    "status_code": 200,
    "ssl_days_remaining": 34,
    "content_valid": true,
    "last_check": "2025-04-22 18:32:01",
    "total_checks": 23,
    "successful_checks": 23,
    "uptime": 100.0,
    "alert_sent": false
  },
  "Tesser": {
    "online": true,
    "error": null,
    "latency": 2716,
    "status_code": 200,
    "ssl_days_remaining": 76,
    "content_valid": true,
    "last_check": "2025-04-22 18:32:04",
    "total_checks": 23,
    "successful_checks": 23,
    "uptime": 100.0,
    "alert_sent": false
  }
}