{
  "Influencers": {
    "online": true,
    "error": null,
    "latency": 850,
    "status_code": 200,
    "ssl_days_remaining": 46,
    "content_valid": true,
    "last_check": "2025-06-11 19:19:03",
    "total_checks": 1120,
    "successful_checks": 1120,
    "uptime": 100.0,
    "alert_sent": false
  },
  "Tesser": {
    "online": true,
    "error": null,
    "latency": 2043,
    "status_code": 200,
    "ssl_days_remaining": 86,
    "content_valid": true,
    "last_check": "2025-06-11 19:19:05",
    "total_checks": 1120,
    "successful_checks": 1119,
    "uptime": 99.91,
    "alert_sent": false
  }
}