{
  "Influencers": {
    "online": true,
    "error": null,
    "latency": 116,
    "status_code": 200,
    "ssl_days_remaining": 84,
    "content_valid": true,
    "last_check": "2025-07-05 15:23:12",
    "total_checks": 1643,
    "successful_checks": 1643,
    "uptime": 100.0,
    "alert_sent": false
  },
  "Tesser": {
    "online": true,
    "error": null,
    "latency": 2315,
    "status_code": 200,
    "ssl_days_remaining": 62,
    "content_valid": true,
    "last_check": "2025-07-05 15:23:15",
    "total_checks": 1643,
    "successful_checks": 1640,
    "uptime": 99.82,
    "alert_sent": false
  }
}