{
  "Influencers": {
    "online": true,
    "error": null,
    "latency": 119,
    "status_code": 200,
    "ssl_days_remaining": 54,
    "content_valid": true,
    "last_check": "2025-06-02 23:23:54",
    "total_checks": 927,
    "successful_checks": 927,
    "uptime": 100.0,
    "alert_sent": false
  },
  "Tesser": {
    "online": true,
    "error": null,
    "latency": 2120,
    "status_code": 200,
    "ssl_days_remaining": 35,
    "content_valid": true,
    "last_check": "2025-06-02 23:23:57",
    "total_checks": 927,
    "successful_checks": 926,
    "uptime": 99.89,
    "alert_sent": false
  }
}