{
  "Influencers": {
    "online": true,
    "error": null,
    "latency": 186,
    "status_code": 200,
    "ssl_days_remaining": 33,
    "content_valid": true,
    "last_check": "2025-04-23 06:32:57",
    "total_checks": 33,
    "successful_checks": 33,
    "uptime": 100.0,
    "alert_sent": false
  },
  "Tesser": {
    "online": true,
    "error": null,
    "latency": 6876,
    "status_code": 200,
    "ssl_days_remaining": 76,
    "content_valid": true,
    "last_check": "2025-04-23 06:33:04",
    "total_checks": 33,
    "successful_checks": 33,
    "uptime": 100.0,
    "alert_sent": false
  }
}