{
  "Influencers": {
    "online": true,
    "error": null,
    "latency": 82,
    "status_code": 200,
    "ssl_days_remaining": 75,
    "content_valid": true,
    "last_check": "2025-05-13 17:21:23",
    "total_checks": 482,
    "successful_checks": 482,
    "uptime": 100.0,
    "alert_sent": false
  },
  "Tesser": {
    "online": true,
    "error": null,
    "latency": 2033,
    "status_code": 200,
    "ssl_days_remaining": 55,
    "content_valid": true,
    "last_check": "2025-05-13 17:21:26",
    "total_checks": 482,
    "successful_checks": 482,
    "uptime": 100.0,
    "alert_sent": false
  }
}