{
  "Influencers": {
    "online": true,
    "error": null,
    "latency": 93,
    "status_code": 200,
    "ssl_days_remaining": 68,
    "content_valid": true,
    "last_check": "2025-05-20 20:26:54",
    "total_checks": 639,
    "successful_checks": 639,
    "uptime": 100.0,
    "alert_sent": false
  },
  "Tesser": {
    "online": true,
    "error": null,
    "latency": 1992,
    "status_code": 200,
    "ssl_days_remaining": 48,
    "content_valid": true,
    "last_check": "2025-05-20 20:26:56",
    "total_checks": 639,
    "successful_checks": 639,
    "uptime": 100.0,
    "alert_sent": false
  }
}