{
  "Influencers": {
    "online": true,
    "error": null,
    "latency": 130,
    "status_code": 200,
    "ssl_days_remaining": 84,
    "content_valid": true,
    "last_check": "2025-05-04 15:22:15",
    "total_checks": 282,
    "successful_checks": 282,
    "uptime": 100.0,
    "alert_sent": false
  },
  "Tesser": {
    "online": true,
    "error": null,
    "latency": 2013,
    "status_code": 200,
    "ssl_days_remaining": 64,
    "content_valid": true,
    "last_check": "2025-05-04 15:22:17",
    "total_checks": 282,
    "successful_checks": 282,
    "uptime": 100.0,
    "alert_sent": false
  }
}