{
  "Influencers": {
    "online": true,
    "error": null,
    "latency": 112,
    "status_code": 200,
    "ssl_days_remaining": 86,
    "content_valid": true,
    "last_check": "2025-05-02 05:22:55",
    "total_checks": 228,
    "successful_checks": 228,
    "uptime": 100.0,
    "alert_sent": false
  },
  "Tesser": {
    "online": true,
    "error": null,
    "latency": 2163,
    "status_code": 200,
    "ssl_days_remaining": 67,
    "content_valid": true,
    "last_check": "2025-05-02 05:22:58",
    "total_checks": 228,
    "successful_checks": 228,
    "uptime": 100.0,
    "alert_sent": false
  }
}