{
  "Influencers": {
    "online": true,
    "error": null,
    "latency": 121,
    "status_code": 200,
    "ssl_days_remaining": 61,
    "content_valid": true,
    "last_check": "2025-05-27 16:30:50",
    "total_checks": 789,
    "successful_checks": 789,
    "uptime": 100.0,
    "alert_sent": false
  },
  "Tesser": {
    "online": true,
    "error": null,
    "latency": 2347,
    "status_code": 200,
    "ssl_days_remaining": 41,
    "content_valid": true,
    "last_check": "2025-05-27 16:30:53",
    "total_checks": 789,
    "successful_checks": 789,
    "uptime": 100.0,
    "alert_sent": false
  }
}