{
  "Influencers": {
    "online": true,
    "error": null,
    "latency": 94,
    "status_code": 200,
    "ssl_days_remaining": 84,
    "content_valid": true,
    "last_check": "2025-07-05 20:24:47",
    "total_checks": 1648,
    "successful_checks": 1648,
    "uptime": 100.0,
    "alert_sent": false
  },
  "Tesser": {
    "online": true,
    "error": null,
    "latency": 2802,
    "status_code": 200,
    "ssl_days_remaining": 62,
    "content_valid": true,
    "last_check": "2025-07-05 20:24:50",
    "total_checks": 1648,
    "successful_checks": 1645,
    "uptime": 99.82,
    "alert_sent": false
  }
}