{
  "Influencers": {
    "online": true,
    "error": null,
    "latency": 177,
    "status_code": 200,
    "ssl_days_remaining": 66,
    "content_valid": true,
    "last_check": "2025-05-22 09:26:15",
    "total_checks": 672,
    "successful_checks": 672,
    "uptime": 100.0,
    "alert_sent": false
  },
  "Tesser": {
    "online": true,
    "error": null,
    "latency": 2091,
    "status_code": 200,
    "ssl_days_remaining": 47,
    "content_valid": true,
    "last_check": "2025-05-22 09:26:18",
    "total_checks": 672,
    "successful_checks": 672,
    "uptime": 100.0,
    "alert_sent": false
  }
}