{
  "Influencers": {
    "online": true,
    "error": null,
    "latency": 286,
    "status_code": 200,
    "ssl_days_remaining": 56,
    "content_valid": true,
    "last_check": "2025-06-01 15:22:34",
    "total_checks": 897,
    "successful_checks": 897,
    "uptime": 100.0,
    "alert_sent": false
  },
  "Tesser": {
    "online": true,
    "error": null,
    "latency": 1977,
    "status_code": 200,
    "ssl_days_remaining": 36,
    "content_valid": true,
    "last_check": "2025-06-01 15:22:36",
    "total_checks": 897,
    "successful_checks": 896,
    "uptime": 99.89,
    "alert_sent": false
  }
}