{
  "Influencers": {
    "online": true,
    "error": null,
    "latency": 123,
    "status_code": 200,
    "ssl_days_remaining": 75,
    "content_valid": true,
    "last_check": "2025-07-14 19:19:13",
    "total_checks": 1843,
    "successful_checks": 1843,
    "uptime": 100.0,
    "alert_sent": false
  },
  "Tesser": {
    "online": true,
    "error": null,
    "latency": 2469,
    "status_code": 200,
    "ssl_days_remaining": 53,
    "content_valid": true,
    "last_check": "2025-07-14 19:19:16",
    "total_checks": 1843,
    "successful_checks": 1840,
    "uptime": 99.84,
    "alert_sent": false
  }
}